MANIFEST.in
README.md
setup.py
ctplib/libthostmduserapi_se.so
ctplib/libthosttraderapi_se.so
src/vnctp.h
src/vnctpmd.cpp
src/vnctpmd.h
src/vnctptd.cpp
src/vnctptd.h
src/ctp/ThostFtdcMdApi.h
src/ctp/ThostFtdcTraderApi.h
src/ctp/ThostFtdcUserApiDataType.h
src/ctp/ThostFtdcUserApiStruct.h
src/pybind11/attr.h
src/pybind11/buffer_info.h
src/pybind11/cast.h
src/pybind11/chrono.h
src/pybind11/common.h
src/pybind11/complex.h
src/pybind11/eigen.h
src/pybind11/embed.h
src/pybind11/eval.h
src/pybind11/functional.h
src/pybind11/iostream.h
src/pybind11/numpy.h
src/pybind11/operators.h
src/pybind11/options.h
src/pybind11/pybind11.h
src/pybind11/pytypes.h
src/pybind11/stl.h
src/pybind11/stl_bind.h
src/pybind11/detail/class.h
src/pybind11/detail/common.h
src/pybind11/detail/descr.h
src/pybind11/detail/init.h
src/pybind11/detail/internals.h
src/pybind11/detail/typeid.h
vnctp/__init__.py
vnctp/constants.py
vnctp.egg-info/PKG-INFO
vnctp.egg-info/SOURCES.txt
vnctp.egg-info/dependency_links.txt
vnctp.egg-info/not-zip-safe
vnctp.egg-info/requires.txt
vnctp.egg-info/top_level.txt