Metadata-Version: 1.0
Name: vnctp
Version: 0.0.3
Summary: CTP binding extracted from vnpy
Home-page: https://github.com/guoxiaoyong/vnctp
Author: Xiaoyong Guo
Author-email: guoxiaoyong@guoxiaoyong.com
License: UNKNOWN
Platform: UNKNOWN
